[1,["f0nNITfgxDiJlXjkO82Iua"],0,[["sp.SkeletonData",["_name","_atlasText","textureNames","_skeletonJson","textures"],-1,3]],[[0,0,1,2,3,4,5]],[[0,"skeleton","\r\nskeleton.png\r\nsize: 237,262\r\nformat: RGBA8888\r\nfilter: Linear,Linear\r\nrepeat: none\r\nimg_cm1\r\n  rotate: false\r\n  xy: 79, 5\r\n  size: 40, 40\r\n  orig: 40, 40\r\n  offset: 0, 0\r\n  index: -1\r\nimg_g\r\n  rotate: true\r\n  xy: 123, 134\r\n  size: 60, 52\r\n  orig: 60, 52\r\n  offset: 0, 0\r\n  index: -1\r\nimg_hpnn\r\n  rotate: false\r\n  xy: 2, 196\r\n  size: 175, 64\r\n  orig: 175, 64\r\n  offset: 0, 0\r\n  index: -1\r\n图层 9792\r\n  rotate: true\r\n  xy: 179, 193\r\n  size: 67, 56\r\n  orig: 67, 56\r\n  offset: 0, 0\r\n  index: -1\r\n图层 9793\r\n  rotate: false\r\n  xy: 162, 6\r\n  size: 39, 40\r\n  orig: 39, 40\r\n  offset: 0, 0\r\n  index: -1\r\n图层 9795\r\n  rotate: false\r\n  xy: 2, 111\r\n  size: 119, 83\r\n  orig: 119, 83\r\n  offset: 0, 0\r\n  index: -1\r\n图层 9796\r\n  rotate: true\r\n  xy: 213, 171\r\n  size: 20, 22\r\n  orig: 20, 22\r\n  offset: 0, 0\r\n  index: -1\r\n图层 9797\r\n  rotate: false\r\n  xy: 177, 140\r\n  size: 34, 51\r\n  orig: 34, 51\r\n  offset: 0, 0\r\n  index: -1\r\n图层 9799\r\n  rotate: true\r\n  xy: 121, 2\r\n  size: 44, 39\r\n  orig: 44, 39\r\n  offset: 0, 0\r\n  index: -1\r\n图层 9800\r\n  rotate: false\r\n  xy: 79, 47\r\n  size: 40, 62\r\n  orig: 40, 62\r\n  offset: 0, 0\r\n  index: -1\r\n图层 9801\r\n  rotate: false\r\n  xy: 123, 48\r\n  size: 99, 84\r\n  orig: 99, 84\r\n  offset: 0, 0\r\n  index: -1\r\n图层 9803\r\n  rotate: true\r\n  xy: 213, 157\r\n  size: 12, 16\r\n  orig: 12, 16\r\n  offset: 0, 0\r\n  index: -1\r\n图层 9804\r\n  rotate: false\r\n  xy: 177, 134\r\n  size: 4, 4\r\n  orig: 4, 4\r\n  offset: 0, 0\r\n  index: -1\r\n圖層 1209\r\n  rotate: true\r\n  xy: 2, 26\r\n  size: 83, 75\r\n  orig: 83, 75\r\n  offset: 0, 0\r\n  index: -1\r\n",["skeleton.png"],{"skeleton":{"hash":"N9DwdNfnGUVfXA5oJKcX1Jd72gU","spine":"3.8.99","x":-104.03,"y":-97.47,"width":190.02,"height":190.43,"images":"","audio":""},"bones":[{"name":"root"},{"name":"图层 9794","parent":"root","x":-76.43,"y":-46.07},{"name":"img_g2","parent":"root","x":-72.74,"y":-46.48},{"name":"圖層 1209","parent":"root","length":34.03,"rotation":89.31,"x":-6.06,"y":-42.11},{"name":"图层 9801","parent":"圖層 1209","length":67.12,"rotation":14.47,"x":34.47,"y":-2.04},{"name":"图层 9799","parent":"圖層 1209","length":34.85,"rotation":-52.44,"x":26.14,"y":-25.19},{"name":"图层 9803","parent":"图层 9799","length":22,"rotation":26.57,"x":36.27,"y":1.97},{"name":"图层 9796","parent":"圖層 1209","length":10.64,"rotation":75.05,"x":9.57,"y":26.77},{"name":"图层 9798","parent":"图层 9796","length":11.15,"rotation":-1.46,"x":12.47,"y":-1.67},{"name":"图层 9804","parent":"图层 9798","length":11.08,"rotation":-33.91,"x":39.7,"y":-27.25},{"name":"图层 9806","parent":"图层 9804","x":13.35,"y":-5.01},{"name":"图层 9793","parent":"root","x":47.85,"y":64.67},{"name":"img_g","parent":"图层 9801","rotation":-103.78,"x":14.12,"y":11.14},{"name":"图层 9792","parent":"root","length":16.74,"rotation":-93.01,"x":32.28,"y":-36.99},{"name":"img_g3","parent":"图层 9792","rotation":93.01,"x":-11.3,"y":-2.21},{"name":"图层 9805","parent":"图层 9801","length":21.3,"rotation":4.45,"x":73.45,"y":-3.92},{"name":"图层 9795","parent":"图层 9805","length":15.45,"rotation":51.78,"x":-33.86,"y":37.64},{"name":"图层 9797","parent":"图层 9795","length":11.62,"rotation":-17.32,"x":16.69,"y":0.45},{"name":"图层 9800","parent":"图层 9797","length":17.43,"rotation":-9.74,"x":11.97,"y":0.27},{"name":"图层 9807","parent":"图层 9805","length":16.75,"rotation":-85.03,"x":-27.93,"y":-25.92,"scaleX":0.4045},{"name":"图层 9808","parent":"图层 9807","length":25.45,"rotation":3.66,"x":15.81,"y":0.27}],"slots":[{"name":"图层 9799","bone":"图层 9799","attachment":"图层 9799"},{"name":"图层 9796","bone":"图层 9796","attachment":"图层 9796"},{"name":"圖層 1209","bone":"圖層 1209","attachment":"圖層 1209"},{"name":"图层 9804","bone":"图层 9806","attachment":"图层 9804"},{"name":"图层 9803","bone":"图层 9804","attachment":"图层 9803"},{"name":"图层 9800","bone":"图层 9803","attachment":"图层 9800"},{"name":"图层 9797","bone":"图层 9798","attachment":"图层 9797"},{"name":"图层 9795","bone":"图层 9808","attachment":"图层 9795"},{"name":"图层 9794","bone":"图层 9794","attachment":"img_cm1"},{"name":"图层 9793","bone":"图层 9793","attachment":"图层 9793"},{"name":"图层 9792","bone":"图层 9792","attachment":"图层 9792"},{"name":"图层 9801","bone":"图层 9801","attachment":"图层 9801"},{"name":"img_hpnn","bone":"root","attachment":"img_hpnn"},{"name":"img_g","bone":"img_g","attachment":"img_g"},{"name":"img_g2","bone":"img_g2","attachment":"img_g"},{"name":"img_g3","bone":"img_g3","attachment":"img_g"}],"skins":[{"name":"default","attachments":{"img_g":{"img_g":{"x":-3.09,"y":1.13,"width":60,"height":52}},"img_g2":{"img_g":{"x":-1.29,"y":0.63,"width":60,"height":52}},"img_g3":{"img_g":{"x":-3.07,"y":1.08,"width":60,"height":52}},"img_hpnn":{"img_hpnn":{"x":-1.51,"y":-65.47,"width":175,"height":64}},"图层 9792":{"图层 9792":{"x":7.58,"y":1.59,"rotation":93.01,"width":67,"height":56}},"图层 9793":{"图层 9793":{"x":-3.6,"y":-5.45,"width":39,"height":40}},"图层 9794":{"img_cm1":{"x":24.07,"width":40,"height":40},"图层 9794":{"x":18.19,"y":2.09,"width":40,"height":40}},"图层 9795":{"图层 9795":{"type":"mesh","hull":88,"width":119,"height":83,"uvs":[0.00591,0.53973,0.04423,0.52874,0.09787,0.51501,0.14386,0.50402,0.17835,0.48479,0.19942,0.47106,0.21283,0.42161,0.22816,0.34744,0.24349,0.27877,0.25307,0.23482,0.2684,0.21009,0.28756,0.22108,0.27414,0.17713,0.29714,0.14417,0.33354,0.10846,0.37377,0.07,0.41784,0.03703,0.45808,0.01231,0.49831,0.00682,0.54046,0.00132,0.58645,0.00407,0.62285,0.01231,0.66308,0.03703,0.69182,0.06176,0.70524,0.08373,0.70008,0.09703,0.68608,0.13318,0.71673,0.10846,0.74164,0.16065,0.75505,0.20185,0.76846,0.24031,0.78187,0.28152,0.79337,0.31997,0.79912,0.35019,0.85468,0.36118,0.90833,0.37217,0.95239,0.37217,0.97155,0.38315,0.98497,0.4326,0.99071,0.4738,0.99838,0.51776,0.99838,0.54248,0.98305,0.59467,0.96006,0.64961,0.93707,0.69356,0.92174,0.72653,0.89108,0.77872,0.87767,0.74576,0.84893,0.68532,0.82594,0.62489,0.81445,0.58643,0.7972,0.50952,0.77613,0.44908,0.77804,0.39414,0.75888,0.36393,0.72631,0.35019,0.68224,0.35019,0.61135,0.36393,0.54621,0.38315,0.51556,0.38865,0.45616,0.42436,0.40635,0.45183,0.36994,0.4793,0.32779,0.52874,0.21475,0.53699,0.20134,0.55072,0.24924,0.58918,0.35845,0.64412,0.36611,0.77597,0.37186,0.84739,0.38335,0.92431,0.38335,0.96826,0.38144,0.99024,0.34695,1,0.30672,1,0.28372,1,0.2454,0.98749,0.20708,0.97101,0.16493,0.94629,0.12278,0.91332,0.09213,0.88311,0.07213,0.85744,0.05572,0.82817,0.03465,0.78147,0.02315,0.7485,0.01357,0.71005,0.00399,0.63862,0.00208,0.58643,0.33908,0.66652,0.34955,0.78447,0.35254,0.86596,0.36899,0.95389,0.79819,0.3963,0.80866,0.46493,0.8281,0.52712,0.84455,0.5936,0.8655,0.65794,0.88345,0.71798,0.89392,0.74158,0.29261,0.83165,0.23277,0.80591,0.18341,0.76517,0.13405,0.70297,0.06375,0.61719,0.91934,0.57644,0.90887,0.48637],"triangles":[43,104,42,41,104,40,35,105,34,105,35,36,40,105,39,36,38,105,37,38,36,39,105,38,42,104,41,43,44,104,40,104,105,34,105,93,105,104,95,46,98,45,47,97,98,98,97,45,45,97,44,48,96,97,97,96,44,49,95,96,44,96,104,96,95,104,95,50,94,95,94,105,51,93,94,93,105,94,52,92,93,93,92,34,92,33,34,81,82,102,82,83,102,83,84,102,102,84,103,84,85,103,85,86,103,3,103,2,1,103,87,87,0,1,103,86,87,103,1,2,78,101,100,78,79,101,79,80,101,80,81,101,81,102,101,66,101,102,65,102,3,102,103,3,73,74,91,91,74,90,90,74,99,74,75,99,75,76,99,99,76,100,76,77,100,77,78,100,69,90,89,90,99,89,89,99,88,88,99,100,68,89,88,66,88,100,100,101,66,66,102,65,47,48,97,48,49,96,50,51,94,51,52,93,33,54,32,92,53,33,52,53,92,72,73,91,91,70,71,72,91,71,63,64,6,6,7,63,63,7,62,62,7,8,62,8,11,8,9,11,62,11,61,61,11,60,60,11,14,11,13,14,59,60,15,60,14,15,15,16,59,16,17,59,17,18,59,59,18,58,18,19,58,57,19,20,57,58,19,56,57,26,21,26,20,26,57,20,32,54,31,54,55,31,55,30,31,55,29,30,55,56,29,29,26,28,29,56,26,26,27,28,22,26,21,9,10,11,11,12,13,26,23,25,26,22,23,25,23,24,91,90,70,90,69,70,89,68,69,88,67,68,53,54,33,49,50,95,46,47,98,88,66,67,65,3,4,65,4,64,64,5,6,4,5,64],"vertices":[1,18,20.54,-0.4,1,4,15,4.09,61.64,0.00608,16,42.33,-14.97,0.00363,17,29.07,-7.09,0.04493,18,18.1,-4.36,0.94536,4,15,3.17,55.22,0.04442,16,36.72,-18.23,0.03516,17,24.68,-11.87,0.26445,18,14.58,-9.81,0.65597,4,15,2.32,49.74,0.12534,16,31.89,-20.95,0.08371,17,20.88,-15.91,0.45546,18,11.52,-14.44,0.33549,4,15,2.56,45.34,0.24834,16,28.58,-23.86,0.0939,17,18.58,-19.67,0.49623,18,9.89,-18.53,0.16152,4,15,2.85,42.6,0.36937,16,26.61,-25.78,0.07178,17,17.28,-22.09,0.47049,18,9.02,-21.14,0.08836,4,15,6.25,39.8,0.52104,16,26.51,-30.19,0.03711,17,18.5,-26.32,0.40795,18,10.94,-25.1,0.03391,4,15,11.53,36.14,0.65009,16,26.9,-36.6,0.01476,17,20.78,-32.33,0.32727,18,14.2,-30.63,0.00788,4,15,16.37,32.63,0.73389,16,27.13,-42.58,0.00558,17,22.78,-37.97,0.2595,18,17.13,-35.85,0.00103,4,15,19.48,30.4,0.77032,16,27.31,-46.39,0.00299,17,24.08,-41.56,0.22662,18,19.02,-39.17,0.00008,3,15,20.86,28.03,0.78478,16,26.3,-48.95,0.00226,17,23.88,-44.3,0.21296,3,15,19.28,26.15,0.80879,16,23.84,-48.87,0.0015,17,21.51,-44.95,0.18971,3,15,23.24,26.52,0.84537,16,26.59,-51.75,0.00035,17,24.99,-46.89,0.15428,3,15,24.99,23.07,0.86566,16,24.95,-55.26,0.00008,17,24.47,-50.72,0.13426,2,15,26.45,18.02,0.90547,17,22.82,-55.7,0.09453,2,15,27.98,12.48,0.94823,17,20.95,-61.15,0.05177,2,15,28.94,6.64,0.98085,17,18.44,-66.5,0.01915,2,15,29.39,1.45,0.9959,17,15.87,-71.03,0.0041,3,15,28.32,-3.24,0.99971,17,12.34,-74.3,0.00009,19,-17.73,58.01,0.0002,2,15,27.19,-8.13,0.99765,19,-12.97,56.45,0.00235,2,15,25.26,-13.23,0.99121,19,-8.06,54.09,0.00879,2,15,23.25,-17.13,0.98297,19,-4.35,51.75,0.01703,2,15,19.81,-21.06,0.96897,19,-0.71,47.98,0.03103,2,15,16.79,-23.73,0.95736,19,1.71,44.75,0.04264,2,15,14.56,-24.7,0.95276,19,2.49,42.44,0.04724,2,15,13.7,-23.74,0.95068,19,1.46,41.67,0.04932,2,15,11.37,-21.12,0.92379,19,-1.42,39.57,0.07621,2,15,12.2,-25.47,0.89271,19,3.13,40.02,0.10729,2,15,7.17,-27.09,0.85922,19,4.38,34.87,0.14078,2,15,3.43,-27.67,0.81022,19,4.73,31.1,0.18978,2,15,-0.08,-28.42,0.74168,19,5.3,27.53,0.25832,2,15,-3.8,-29.21,0.64222,19,5.96,23.76,0.35778,2,15,-7.22,-29.97,0.51227,19,6.71,20.29,0.48773,2,15,-9.77,-30.29,0.35194,19,7.11,17.72,0.64806,3,15,-12.23,-41.75,0.02498,19,21.83,14.27,0.22302,20,8.96,13.46,0.752,3,15,-14.61,-53.18,0.00605,19,36.7,10.92,0.24195,20,22.34,9.24,0.752,1,20,34.09,6.42,1,1,20,38.27,4.41,1,1,20,37.62,0.04,1,1,20,35.63,-3.25,1,1,20,33.91,-6.86,1,1,20,31.8,-8.61,1,2,19,39.73,-9.56,0.032,20,23.24,-11.33,0.968,2,19,29.07,-12.67,0.2,20,12.41,-13.76,0.8,2,19,19.3,-14.95,0.536,20,2.51,-15.41,0.464,1,19,12.49,-16.74,1,1,15,-47.15,-27.59,1,1,15,-44.05,-26.93,1,1,15,-38.22,-25.25,1,1,15,-32.6,-24.22,1,1,15,-29.14,-23.92,1,1,15,-22.43,-23.97,1,1,15,-16.88,-23.15,1,1,15,-12.62,-24.8,1,1,15,-9.53,-23.42,1,1,15,-7.23,-20.09,1,1,15,-5.59,-15.11,1,1,15,-4.04,-6.74,1,3,15,-3.13,1.13,0.99661,17,-11.12,-52.9,0.00279,19,-24.81,27.06,0.0006,1,15,-2.42,4.73,1,1,15,-3.02,12.37,1,1,15,-3.33,18.71,1,1,15,-4.14,23.54,1,1,15,-6.47,29.59,1,1,15,-2.91,42.58,1,1,15,-3.5,44.45,1,1,15,-8.31,40.04,1,1,15,-16.71,29.12,1,1,15,-27.39,31.68,1,2,15,-33.23,32.88,0.968,16,-3.35,-3.44,0.032,1,15,-39.72,33.58,1,1,15,-43.19,34.72,1,1,15,-44.85,35.51,1,2,16,-4.89,9.47,0.9879,17,-23.29,2.19,0.0121,2,16,-0.39,11.11,0.93858,17,-19.48,5.09,0.06142,3,16,2.18,12.05,0.88938,17,-17.31,6.75,0.10937,18,-29.95,1.43,0.00125,3,16,6.82,12.63,0.73264,17,-13.05,8.69,0.25269,18,-26.08,4.06,0.01467,3,16,11.57,12.9,0.47353,17,-8.59,10.36,0.47061,18,-21.97,6.47,0.05586,3,16,16.99,12.69,0.16242,17,-3.36,11.77,0.6748,18,-17.05,8.74,0.16278,3,16,22.64,11.83,0.01241,17,2.29,12.63,0.61113,18,-11.63,10.55,0.37646,2,17,6.71,12.85,0.37939,18,-7.31,11.51,0.62061,2,17,9.85,13.24,0.22125,18,-4.28,12.43,0.77875,2,17,12.92,11.85,0.09046,18,-1.02,11.57,0.90954,2,17,17.26,10.28,0.00235,18,3.52,10.77,0.99765,1,18,6.46,9.91,1,1,18,9.57,8.56,1,1,18,14.69,5.36,1,1,18,18.01,2.57,1,3,15,-17.75,31.89,0.0026,16,5.45,-16.22,0.92014,17,-5.77,-19.26,0.07727,3,15,-27.44,33.77,0.00001,16,0.93,-7.44,0.99871,17,-12.7,-12.23,0.00128,1,16,-1.72,-1.21,1,1,15,-41.52,35.97,1,2,15,-13.42,-28.49,0.22223,19,4.73,14.24,0.77777,2,15,-19.26,-27.4,0.08186,19,2.84,8.52,0.91814,2,15,-24.87,-28.17,0.01396,19,3.25,2.86,0.98604,1,19,2.37,-2.98,1,1,19,2.83,-8.87,1,1,19,2.83,-14.3,1,1,19,3.75,-16.59,1,2,15,-29.04,41.43,0.00001,16,5.96,-1.45,0.99999,2,15,-24.78,47.53,0.00022,16,13.38,-1.02,0.99978,3,15,-19.73,52.05,0.00092,16,20.06,-2.19,0.12132,17,4,-1.52,0.87776,3,15,-12.99,56.01,0.00338,16,27.34,-5.04,0.02452,17,11.8,-2.07,0.97209,4,15,-3.61,61.73,0.00212,16,37.64,-8.87,0.0019,17,22.77,-2.66,0.02146,18,11.14,-1.06,0.97453,2,19,23.98,-5.18,0.232,20,7.8,-5.96,0.768,3,15,-23.88,-47.41,0.00067,19,28.33,2.18,0.18333,20,12.71,1.1,0.816],"edges":[0,2,2,4,4,6,6,8,8,10,10,12,12,14,14,16,16,18,18,20,20,22,22,24,24,26,26,28,28,30,30,32,32,34,34,36,36,38,38,40,40,42,42,44,44,46,46,48,48,50,50,52,52,54,54,56,56,58,58,60,60,62,62,64,64,66,66,68,68,70,70,72,72,74,74,76,76,78,78,80,80,82,82,84,84,86,86,88,88,90,90,92,92,94,94,96,96,98,98,100,100,102,102,104,104,106,106,108,108,110,110,112,112,114,114,116,116,118,118,120,120,122,122,124,124,126,126,128,128,130,130,132,132,134,134,136,136,138,138,140,140,142,142,144,144,146,146,148,148,150,150,152,152,154,154,156,156,158,158,160,160,162,162,164,164,166,166,168,168,170,170,172,172,174,0,174,8,130,182,144,182,180,180,178,178,176,194,196,192,194,190,192,188,190,186,188,184,186,184,106,66,106,66,184]}},"图层 9796":{"图层 9796":{"x":4.83,"y":1.31,"rotation":-164.36,"width":20,"height":22}},"图层 9797":{"图层 9797":{"x":16.71,"y":-6.87,"rotation":-162.9,"width":34,"height":51}},"图层 9799":{"图层 9799":{"x":20.3,"y":-1.96,"rotation":-36.87,"width":44,"height":39}},"图层 9800":{"图层 9800":{"x":24.87,"y":-0.84,"rotation":-63.43,"width":40,"height":62}},"图层 9801":{"图层 9801":{"type":"mesh","hull":99,"width":99,"height":84,"uvs":[0.21071,0.43517,0.18304,0.46574,0.17225,0.47767,0.13138,0.51167,0.09572,0.53355,0.07368,0.557,0.09118,0.56858,0.13138,0.57117,0.15782,0.57967,0.18907,0.591,0.22994,0.59384,0.25639,0.5825,0.25639,0.625,0.25419,0.6845,0.2612,0.74117,0.28283,0.79217,0.29966,0.8375,0.3261,0.87717,0.36457,0.91684,0.41746,0.95367,0.46313,0.97634,0.51362,0.99617,0.5593,1,0.61699,1,0.66507,1,0.72037,0.9905,0.77085,0.96784,0.82374,0.92817,0.85847,0.89496,0.89586,0.8586,0.93279,0.79705,0.94635,0.761,0.95596,0.70717,0.96317,0.6675,0.96558,0.5995,0.95837,0.56267,0.94154,0.52017,0.92952,0.489,0.9199,0.46067,0.89827,0.44367,0.93437,0.44618,0.96317,0.43517,0.98722,0.41534,1,0.3955,1,0.35922,0.97039,0.35017,0.92952,0.33884,0.89827,0.33317,0.86942,0.31617,0.90067,0.29917,0.93192,0.26517,0.94394,0.234,0.95596,0.19434,0.95837,0.16884,0.96077,0.12634,0.95837,0.098,0.93913,0.05267,0.92471,0.02717,0.91029,0.01017,0.89346,0,0.86461,0,0.8574,0.04417,0.86221,0.0895,0.86461,0.12917,0.84538,0.15184,0.82134,0.16884,0.79008,0.16317,0.76124,0.14617,0.73479,0.12634,0.69633,0.11784,0.65546,0.10934,0.61219,0.11217,0.5617,0.1235,0.50881,0.132,0.45592,0.14617,0.40784,0.166,0.37419,0.18584,0.33091,0.21134,0.29966,0.23117,0.2612,0.26517,0.23235,0.2935,0.18667,0.29634,0.14821,0.29067,0.11936,0.27084,0.09772,0.24817,0.0833,0.21984,0.07849,0.18017,0.07368,0.1575,0.05204,0.14334,0.03281,0.15184,0.01598,0.18584,0.00637,0.2255,0,0.27084,0.00768,0.33727,0.028,0.39267,0.04483,0.421,0.0881,0.45217,0.13138,0.46067,0.17113,0.45576,0.39099,0.48915,0.38638,0.45839,0.39406,0.4222,0.41095,0.39505,0.43244,0.38239,0.45701,0.37696,0.48618,0.37696,0.51074,0.39324,0.52917,0.40772,0.54606,0.43848,0.51074,0.45477,0.47543,0.462,0.44472,0.47467,0.41555,0.48915,0.3219,0.31,0.38331,0.32629,0.43398,0.32991,0.48771,0.32991,0.51996,0.34077,0.54299,0.37334,0.55066,0.40772,0.30654,0.4421,0.31115,0.37696,0.31883,0.52172,0.87462,0.6321,0.68595,0.39963,0.69274,0.36097,0.71084,0.3263,0.7312,0.29963,0.76514,0.29297,0.79795,0.29963,0.83189,0.32363,0.83641,0.35697,0.81831,0.37297,0.78777,0.38897,0.75609,0.39697,0.72781,0.40363,0.70631,0.40763,0.6735,0.33697,0.69274,0.2823,0.70405,0.27963,0.73573,0.23563,0.77758,0.2103,0.79569,0.22497,0.80474,0.26363,0.82623,0.30097,0.84433,0.3223],"triangles":[59,62,61,60,59,61,55,63,62,58,62,59,57,62,58,56,62,57,55,62,56,63,55,54,53,63,54,52,63,53,141,67,66,142,66,65,141,66,142,52,64,63,51,64,52,140,68,67,140,67,141,143,142,65,50,64,51,69,140,138,140,69,68,138,70,69,139,138,140,142,128,140,142,140,141,128,142,143,127,139,140,49,64,50,65,64,49,143,65,49,128,127,140,129,128,143,144,129,143,49,144,143,113,78,77,79,78,113,48,144,49,145,144,48,130,144,145,115,114,76,77,76,114,113,77,114,126,139,127,138,139,126,116,74,73,115,75,74,75,115,76,74,116,115,138,71,70,137,138,126,89,93,91,92,91,93,117,73,72,116,73,117,138,72,71,138,117,72,137,117,138,131,130,145,125,137,126,130,132,129,130,129,144,132,130,131,118,117,137,104,115,116,113,80,79,121,113,114,121,80,113,105,104,116,105,116,117,106,105,117,115,102,114,103,115,104,133,128,129,133,129,132,90,89,91,84,94,93,89,88,87,89,86,93,87,86,89,85,93,86,118,106,117,103,102,115,101,121,114,45,44,43,134,127,128,134,128,133,126,127,134,135,125,126,124,137,125,125,136,124,119,118,137,126,134,135,135,136,125,124,119,137,107,106,118,119,107,118,42,45,43,95,94,82,85,84,93,83,94,84,102,101,114,0,81,80,0,80,121,41,46,45,41,45,42,108,107,119,120,0,121,120,121,101,39,47,46,145,48,47,40,39,46,41,40,46,82,96,95,83,82,94,109,106,107,110,105,106,109,107,108,98,82,81,98,81,0,97,96,82,100,120,101,98,97,82,110,104,105,109,110,106,110,111,103,110,103,104,102,103,111,101,102,111,100,101,111,112,100,111,99,100,112,122,120,100,122,100,99,6,5,4,8,7,3,4,3,7,6,4,7,2,8,3,122,11,0,122,0,120,1,0,11,10,2,1,9,8,2,2,10,9,1,11,10,12,11,122,47,39,145,37,123,39,37,39,38,123,37,36,123,36,35,123,35,34,39,131,145,39,132,131,39,133,132,123,133,39,33,123,34,32,123,33,122,13,12,15,14,13,31,123,32,13,99,15,30,123,31,99,16,15,29,123,30,13,122,99,112,17,16,108,119,124,136,108,124,123,134,133,28,123,29,134,123,135,112,18,17,28,27,123,123,136,135,19,112,111,123,108,136,123,26,108,108,25,109,99,112,16,19,18,112,123,27,26,109,20,111,19,111,20,109,111,110,21,20,22,108,26,25,20,109,22,109,23,22,109,24,23,25,24,109],"vertices":[54.45,30.52,52.61,33.79,51.89,35.07,50.08,39.68,48.62,42.73,47.74,46.13,46.02,45.08,45.23,40.87,43.91,38.5,42.25,35.72,41.05,31.84,41.35,29.07,37.89,29.93,32.97,30.88,28.3,31.79,23.62,30.73,19.53,30.02,15.67,28.27,11.53,25.36,7.27,21.02,4.35,17.08,1.54,12.62,0.15,8.3,-1.21,2.76,-2.35,-1.87,-2.87,-7.37,-2.22,-12.68,-0.23,-18.56,1.81,-23.23,3.16,-26.74,7.57,-31.74,10.52,-33.69,14.68,-35.69,17.75,-37.18,23.24,-38.77,26.42,-38.82,30.28,-38.05,33.11,-37.52,35.64,-37.16,37.54,-35.42,37.08,-38.99,36.7,-41.83,37.75,-44.54,39.07,-46.17,42.77,-47.07,43.47,-44.23,45.36,-40.52,46.56,-37.63,48.62,-35.2,49.27,-38.54,51.31,-42.23,53.57,-44.01,56.52,-45.96,58.55,-46.7,61.96,-47.78,64.32,-48.12,68.48,-47.17,70.9,-46.3,72.62,-45.25,73.85,-43.84,74.53,-41.06,71.1,-39.48,67.29,-39.04,63.99,-38.48,62.6,-36.17,61.78,-33.52,62.98,-30.63,65.04,-28.2,67.29,-26.05,68.89,-22.52,70.54,-18.76,71.33,-14.55,71.6,-9.47,72.15,-4.21,72.24,1.16,71.76,6.18,70.94,9.81,69.88,14.48,68.99,17.88,67.13,22.26,65.5,25.6,66.34,30.05,67.71,33.64,70.01,36.01,72.37,37.64,75.02,38.46,78.37,38.13,80.33,38.14,82,39.93,81.76,41.95,79.38,44.25,76.37,45.97,72.83,47.49,66.82,48.96,62.23,47.24,59.52,46.18,55.95,42.65,54.24,38.66,53.7,34.74,45.79,14.26,48.41,14.09,51.18,12.63,53,10.46,53.53,8.14,53.39,5.67,52.7,2.87,50.79,0.83,49.18,-0.65,46.27,-1.66,45.77,2.06,46.02,5.6,45.71,8.81,45.21,11.9,61.19,17.69,58.97,11.82,57.77,6.94,56.5,1.78,54.86,-1.1,51.66,-2.67,48.67,-2.72,51.62,21.44,56.83,19.7,44.84,21.85,22.79,-29.65,46.14,-15.89,49.13,-17.31,51.54,-19.75,53.23,-22.24,52.97,-25.64,51.66,-28.66,48.9,-31.44,46.07,-31.21,45.19,-29.15,44.61,-25.9,44.71,-22.7,44.83,-19.84,45.01,-17.7,51.55,-15.94,55.55,-18.89,55.5,-20.03,58.35,-23.95,59.43,-28.49,57.8,-29.93,54.43,-30.03,50.88,-31.35,48.71,-32.66],"edges":[4,6,6,8,8,10,10,12,12,14,14,16,16,18,18,20,20,22,22,24,24,26,26,28,28,30,30,32,32,34,34,36,36,38,38,40,40,42,42,44,44,46,46,48,48,50,50,52,52,54,54,56,56,58,58,60,60,62,62,64,64,66,66,68,68,70,70,72,72,74,74,76,76,78,82,84,84,86,86,88,88,90,90,92,92,94,94,96,96,98,98,100,100,102,102,104,104,106,106,108,108,110,110,112,112,114,114,116,116,118,118,120,120,122,122,124,124,126,126,128,128,130,130,132,132,134,134,136,136,138,138,140,140,142,142,144,144,146,146,148,148,150,150,152,152,154,154,156,156,158,158,160,160,162,162,164,164,166,166,168,168,170,170,172,172,174,174,176,176,178,178,180,180,182,182,184,184,186,186,188,188,190,190,192,192,194,0,2,2,4,194,196,0,196,78,80,80,82,216,52,276,278]}},"图层 9803":{"图层 9803":{"x":5.45,"y":-0.42,"rotation":-128.99,"width":12,"height":16}},"图层 9804":{"图层 9804":{"x":0.51,"y":-0.18,"rotation":99.93,"width":4,"height":4}},"圖層 1209":{"圖層 1209":{"x":24.01,"y":1.24,"rotation":-89.31,"width":83,"height":75}}}}],"animations":{"animation":{"slots":{"图层 9803":{"color":[{"color":"ffffff00"}]},"图层 9804":{"color":[{"color":"ffffff00"}]}},"bones":{"圖層 1209":{"translate":[{"y":-2.2},{"time":1.3333,"y":4.4},{"time":2.6667,"y":-2.2}]},"img_g2":{"rotate":[{"time":0.3333},{"time":0.8,"angle":-84.81},{"time":1.5},{"time":1.9667,"angle":-84.81}],"scale":[{"x":0,"y":0,"curve":"stepped"},{"time":0.3333,"x":0,"y":0},{"time":0.5667},{"time":0.8,"x":0,"y":0,"curve":"stepped"},{"time":1.5,"x":0,"y":0},{"time":1.7333},{"time":1.9667,"x":0,"y":0}]},"img_g3":{"rotate":[{"time":0.8},{"time":1.3,"angle":180},{"time":2.1},{"time":2.6,"angle":180}],"scale":[{"x":0,"y":0,"curve":"stepped"},{"time":0.8,"x":0,"y":0},{"time":1.1},{"time":1.3,"x":0,"y":0,"curve":"stepped"},{"time":2.1,"x":0,"y":0},{"time":2.4},{"time":2.6,"x":0,"y":0}]},"img_g":{"rotate":[{"time":0.1},{"time":0.6667,"angle":-143.54},{"time":1.5},{"time":2.0667,"angle":-143.54}],"scale":[{"x":0,"y":0,"curve":"stepped"},{"time":0.1,"x":0,"y":0},{"time":0.3667},{"time":0.6667,"x":0,"y":0,"curve":"stepped"},{"time":1.5,"x":0,"y":0},{"time":1.7667},{"time":2.0667,"x":0,"y":0}]},"图层 9792":{"translate":[{"x":0.77,"y":6.38},{"time":0.7},{"time":2.0333,"x":1.32,"y":11},{"time":2.6667,"x":0.77,"y":6.38}]},"图层 9794":{"translate":[{"x":-0.25,"y":0.33},{"time":0.1667},{"time":1.5,"x":-3.96,"y":5.28},{"time":2.6667,"x":-0.25,"y":0.33}]},"图层 9801":{"rotate":[{},{"time":1.3333,"angle":-5.37},{"time":2.6667}]},"图层 9803":{"rotate":[{},{"time":1.3333,"angle":-4.93},{"time":2.6667}]},"图层 9799":{"rotate":[{},{"time":1.3333,"angle":-2.72},{"time":2.6667}]},"图层 9796":{"rotate":[{},{"time":1.3333,"angle":-0.54},{"time":2.6667}],"translate":[{"x":0.94,"y":1.61}]},"图层 9798":{"rotate":[{},{"time":1.3333,"angle":9.66},{"time":2.6667}]},"图层 9804":{"translate":[{"time":1.1667,"x":-8.98,"y":5.57},{"time":2.2667,"x":-1.66,"y":-9.46}],"scale":[{"time":1.1667,"x":0,"y":0},{"time":1.5}]},"图层 9806":{"translate":[{"time":1.2667},{"time":2.3,"x":-0.54,"y":-0.37}]},"图层 9795":{"rotate":[{"angle":6.8},{"time":1.3333,"angle":2.17},{"time":2.6667,"angle":6.8}],"scale":[{},{"time":1.3333,"x":0.93},{"time":2.6667}]},"图层 9793":{"translate":[{"x":1.08,"y":1.3,"curve":0.291,"c2":0.56,"c3":0.62},{"time":0.5,"curve":0.25,"c3":0.75},{"time":1.8333,"x":4.89,"y":5.87,"curve":0.285,"c3":0.6,"c4":0.57},{"time":2.6667,"x":1.08,"y":1.3}]},"图层 9808":{"rotate":[{},{"time":1.3333,"angle":5.42},{"time":2.6667}]},"图层 9807":{"rotate":[{},{"time":1.3333,"angle":6.14},{"time":2.6667}]},"图层 9797":{"rotate":[{},{"time":1.3333,"angle":-3.83},{"time":2.6667}]},"图层 9800":{"rotate":[{},{"time":1.3333,"angle":-7.73},{"time":2.6667}]}},"deform":{"default":{"图层 9801":{"图层 9801":[{"time":1.8333},{"time":1.8667,"offset":200,"curve":"stepped","vertices":[-2.50095,0.07601,-5.21133,-0.65173,-6.86505,-0.38608,-7.32647,0.38842,-6.87345,0.25628,-6.43146,0.56436,-4.45824,0.83608,-2.4773,0.46191,0,0,0.40624,-0.07971,0,0,0,0,0.4151,-0.03456,0,0,0,0,0,0,0,0,0,0,0,0,0,0,0,0,0,0,0,0,0,0,0,0,-3.88692,-0.33319,-6.71276,-0.21317,-8.08836,-0.60769,-8.13367,0.45866,-6.60612,1.23174]},{"time":1.9333,"offset":200,"vertices":[-2.50095,0.07601,-5.21133,-0.65173,-6.86505,-0.38608,-7.32647,0.38842,-6.87345,0.25628,-6.43146,0.56436,-4.45824,0.83608,-2.4773,0.46191,0,0,0.40624,-0.07971,0,0,0,0,0.4151,-0.03456,0,0,0,0,0,0,0,0,0,0,0,0,0,0,0,0,0,0,0,0,0,0,0,0,-3.88692,-0.33319,-6.71276,-0.21317,-8.08836,-0.60769,-8.13367,0.45866,-6.60612,1.23174]},{"time":1.9667}]}}}}}},[0]]],0,0,[0],[-1],[0]]