{
  "projectPath": "D:\\cocos\\chinared",
  "actualPlatform": "web-mobile",
  "mtimes": {
    "6e9612e2-4991-49a5-acdc-1ef9e5b84f44": {
      "assetMtime": 1643089432850,
      "metaMtime": 1643167971699
    },
    "0c829679-e281-4015-a0ed-7c762d86c6bc": {
      "assetMtime": 1643089432851,
      "metaMtime": 1643167971720
    },
    "36d9cbaa-4a8e-4a43-820d-ea328656dc53": {
      "assetMtime": 1643089432851,
      "metaMtime": 1643167971720
    },
    "19f4b53e-6352-48c3-a060-5e7b37f2127f": {
      "assetMtime": 1643089432854,
      "metaMtime": 1643167971755
    },
    "8b7d20f1-d09e-4ce3-bc6c-69cf3e654262": {
      "assetMtime": 1643089432854,
      "metaMtime": 1643167971755
    },
    "2e74bdd3-870b-4a30-bd3a-90755206f531": {
      "assetMtime": 1643089432852,
      "metaMtime": 1643167971732
    },
    "f56fad9a-db40-4940-bc07-1fe98329b963": {
      "assetMtime": 1643089432852,
      "metaMtime": 1643167971732
    },
    "362200f0-28eb-49c3-b855-83904801afe7": {
      "assetMtime": 1643089432856,
      "metaMtime": 1643167971767
    },
    "9e477f8f-7726-4b43-aa2b-4b04d5dd5f77": {
      "assetMtime": 1643089432856,
      "metaMtime": 1643167971767
    },
    "47ae7542-1b65-4daa-84e0-8688fa54bf59": {
      "assetMtime": 1643089432857,
      "metaMtime": 1643167971789
    },
    "70dbc63d-cd2b-4b33-90d9-c276b535b1d2": {
      "assetMtime": 1643089432857,
      "metaMtime": 1643167971789
    },
    "51275146-cf42-4066-ab13-27d7808bf46c": {
      "assetMtime": 1643089432853,
      "metaMtime": 1643167971745
    },
    "6d318825-9b05-4026-9c18-0857a621fab7": {
      "assetMtime": 1643089432853,
      "metaMtime": 1643167971745
    },
    "634ed800-76d2-4f71-ab5b-08de17c1460c": {
      "assetMtime": 1643089432856,
      "metaMtime": 1643167971778
    },
    "015c1f4e-0930-42c8-9b82-cad67b422064": {
      "assetMtime": 1643089432856,
      "metaMtime": 1643167971778
    },
    "854dba15-39b9-4d28-8fca-57bcad564ff4": {
      "assetMtime": 1643089432850,
      "metaMtime": 1643167971710
    },
    "9d0f0a50-73da-4492-8158-d1bd08133665": {
      "assetMtime": 1643089432850,
      "metaMtime": 1643167971710
    },
    "8acd951f-9d4b-4208-b8a4-5fad2123ebb4": {
      "assetMtime": 1643089432855,
      "metaMtime": 1643167971769
    },
    "d1abf658-f9ec-4395-8d6b-7e541f72fae2": {
      "assetMtime": 1643089432855,
      "metaMtime": 1643167971769
    },
    "9a8c9bec-d6c3-4e37-a330-83d990876456": {
      "assetMtime": 1643089432853,
      "metaMtime": 1643167971743
    },
    "16f4bb76-abd0-4016-b27e-4e95ee24177a": {
      "assetMtime": 1643089432853,
      "metaMtime": 1643167971743
    },
    "bec726a5-d6fc-48c5-a13f-af678c721402": {
      "assetMtime": 1643089432858,
      "metaMtime": 1643167971801
    },
    "cf1ffa6c-d540-4bda-a508-006e5739ae5d": {
      "assetMtime": 1643089432858,
      "metaMtime": 1643167971801
    },
    "e02a6708-9d31-4aae-8884-6c7afb162f3a": {
      "assetMtime": 1643089432852,
      "metaMtime": 1643167971731
    },
    "b488900a-1619-4a37-bbbe-6d1680e0416a": {
      "assetMtime": 1643089432852,
      "metaMtime": 1643167971731
    },
    "e0c6b4c9-7d55-44f7-93a1-192cd9d13194": {
      "assetMtime": 1643089432856,
      "metaMtime": 1643167971780
    },
    "70c3d8bc-2112-4926-bded-65c62d8be107": {
      "assetMtime": 1643089432856,
      "metaMtime": 1643167971780
    },
    "e21f1c12-dca1-4a7f-bcf2-1ccdf980ffa5": {
      "assetMtime": 1643089432857,
      "metaMtime": 1643167971788
    },
    "1248025e-ac39-45b8-a121-6062e6b7f156": {
      "assetMtime": 1643089432857,
      "metaMtime": 1643167971788
    },
    "eaee3e7d-22ab-4a48-ac7c-ed652d098303": {
      "assetMtime": 1643089432855,
      "metaMtime": 1643167971757
    },
    "52fcb99f-b299-47fc-b6c6-c0350c3dba61": {
      "assetMtime": 1643089432855,
      "metaMtime": 1643167971757
    },
    "f98de3bb-5542-459b-a214-000f0647f462": {
      "assetMtime": 1643089432851,
      "metaMtime": 1643167971722
    },
    "964aca90-0c59-491b-b49f-7508e3c1cc07": {
      "assetMtime": 1643089432851,
      "metaMtime": 1643167971722
    }
  },
  "result": {
    "name": "game_head_kuang",
    "width": 1024,
    "height": 1024,
    "ver": "1.2.1",
    "uuid": "6e9612e2-4991-49a5-acdc-1ef9e5b84f44",
    "maxWidth": 1024,
    "maxHeight": 1024,
    "padding": 2,
    "allowRotation": true,
    "forceSquared": false,
    "powerOfTwo": false,
    "algorithm": "MaxRects",
    "format": "png",
    "quality": 80,
    "contourBleed": true,
    "paddingBleed": true,
    "filterUnused": true,
    "packable": false,
    "premultiplyAlpha": false,
    "filterMode": "bilinear",
    "platformSettings": {},
    "subMetas": {},
    "bleed": 1,
    "atlases": [
      {
        "files": [
          {
            "name": "txkuang_vip15",
            "uuid": "19f4b53e-6352-48c3-a060-5e7b37f2127f",
            "textureUuid": "8b7d20f1-d09e-4ce3-bc6c-69cf3e654262",
            "path": "D:\\cocos\\chinared\\temp\\trimImages\\spritesheet_js_1643348152144_image_1.png",
            "trim": {
              "x": 3,
              "y": 3,
              "width": 159,
              "height": 153,
              "rotatedWidth": 159,
              "rotatedHeight": 153
            },
            "rawWidth": 160,
            "rawHeight": 160,
            "width": 165,
            "height": 159,
            "originalPath": "D:/cocos/chinared/library/imports/8b/8b7d20f1-d09e-4ce3-bc6c-69cf3e654262.png",
            "x": 0,
            "y": 0,
            "rotatedWidth": 165,
            "rotatedHeight": 159
          },
          {
            "name": "txkuang_vip14",
            "uuid": "51275146-cf42-4066-ab13-27d7808bf46c",
            "textureUuid": "6d318825-9b05-4026-9c18-0857a621fab7",
            "path": "D:\\cocos\\chinared\\temp\\trimImages\\spritesheet_js_1643348152144_image_5.png",
            "trim": {
              "x": 168,
              "y": 3,
              "width": 158,
              "height": 148,
              "rotatedWidth": 158,
              "rotatedHeight": 148
            },
            "rawWidth": 160,
            "rawHeight": 160,
            "width": 164,
            "height": 154,
            "originalPath": "D:/cocos/chinared/library/imports/6d/6d318825-9b05-4026-9c18-0857a621fab7.png",
            "x": 165,
            "y": 0,
            "rotatedWidth": 164,
            "rotatedHeight": 154
          },
          {
            "name": "txkuang_vip12",
            "uuid": "2e74bdd3-870b-4a30-bd3a-90755206f531",
            "textureUuid": "f56fad9a-db40-4940-bc07-1fe98329b963",
            "path": "D:\\cocos\\chinared\\temp\\trimImages\\spritesheet_js_1643348152144_image_2.png",
            "trim": {
              "x": 332,
              "y": 3,
              "width": 156,
              "height": 149,
              "rotatedWidth": 156,
              "rotatedHeight": 149
            },
            "rawWidth": 160,
            "rawHeight": 160,
            "width": 162,
            "height": 155,
            "originalPath": "D:/cocos/chinared/library/imports/f5/f56fad9a-db40-4940-bc07-1fe98329b963.png",
            "x": 329,
            "y": 0,
            "rotatedWidth": 162,
            "rotatedHeight": 155
          },
          {
            "name": "txkuang_vip11",
            "uuid": "e02a6708-9d31-4aae-8884-6c7afb162f3a",
            "textureUuid": "b488900a-1619-4a37-bbbe-6d1680e0416a",
            "path": "D:\\cocos\\chinared\\temp\\trimImages\\spritesheet_js_1643348152145_image_11.png",
            "trim": {
              "x": 168,
              "y": 157,
              "width": 153,
              "height": 151,
              "rotatedWidth": 153,
              "rotatedHeight": 151
            },
            "rawWidth": 160,
            "rawHeight": 160,
            "width": 159,
            "height": 157,
            "originalPath": "D:/cocos/chinared/library/imports/b4/b488900a-1619-4a37-bbbe-6d1680e0416a.png",
            "x": 165,
            "y": 154,
            "rotatedWidth": 159,
            "rotatedHeight": 157
          },
          {
            "name": "txkuang_vip10",
            "uuid": "0c829679-e281-4015-a0ed-7c762d86c6bc",
            "textureUuid": "36d9cbaa-4a8e-4a43-820d-ea328656dc53",
            "path": "D:\\cocos\\chinared\\temp\\trimImages\\spritesheet_js_1643348152144_image_0.png",
            "trim": {
              "x": 3,
              "y": 162,
              "width": 156,
              "height": 148,
              "rotatedWidth": 156,
              "rotatedHeight": 148
            },
            "rawWidth": 160,
            "rawHeight": 160,
            "width": 162,
            "height": 154,
            "originalPath": "D:/cocos/chinared/library/imports/36/36d9cbaa-4a8e-4a43-820d-ea328656dc53.png",
            "x": 0,
            "y": 159,
            "rotatedWidth": 162,
            "rotatedHeight": 154
          },
          {
            "name": "txkuang_vip13",
            "uuid": "9a8c9bec-d6c3-4e37-a330-83d990876456",
            "textureUuid": "16f4bb76-abd0-4016-b27e-4e95ee24177a",
            "path": "D:\\cocos\\chinared\\temp\\trimImages\\spritesheet_js_1643348152145_image_9.png",
            "trim": {
              "x": 327,
              "y": 158,
              "width": 156,
              "height": 141,
              "rotatedWidth": 156,
              "rotatedHeight": 141
            },
            "rawWidth": 160,
            "rawHeight": 160,
            "width": 162,
            "height": 147,
            "originalPath": "D:/cocos/chinared/library/imports/16/16f4bb76-abd0-4016-b27e-4e95ee24177a.png",
            "x": 324,
            "y": 155,
            "rotatedWidth": 162,
            "rotatedHeight": 147
          },
          {
            "name": "txkuang_vip9",
            "uuid": "bec726a5-d6fc-48c5-a13f-af678c721402",
            "textureUuid": "cf1ffa6c-d540-4bda-a508-006e5739ae5d",
            "path": "D:\\cocos\\chinared\\temp\\trimImages\\spritesheet_js_1643348152145_image_10.png",
            "trim": {
              "x": 327,
              "y": 305,
              "width": 142,
              "height": 142,
              "rotatedWidth": 142,
              "rotatedHeight": 142
            },
            "rawWidth": 160,
            "rawHeight": 160,
            "width": 148,
            "height": 148,
            "originalPath": "D:/cocos/chinared/library/imports/cf/cf1ffa6c-d540-4bda-a508-006e5739ae5d.png",
            "x": 324,
            "y": 302,
            "rotatedWidth": 148,
            "rotatedHeight": 148
          },
          {
            "name": "txkuang_vip6",
            "uuid": "e0c6b4c9-7d55-44f7-93a1-192cd9d13194",
            "textureUuid": "70c3d8bc-2112-4926-bded-65c62d8be107",
            "path": "D:\\cocos\\chinared\\temp\\trimImages\\spritesheet_js_1643348152145_image_12.png",
            "trim": {
              "x": 165,
              "y": 314,
              "width": 141,
              "height": 141,
              "rotatedWidth": 141,
              "rotatedHeight": 141
            },
            "rawWidth": 160,
            "rawHeight": 160,
            "width": 147,
            "height": 147,
            "originalPath": "D:/cocos/chinared/library/imports/70/70c3d8bc-2112-4926-bded-65c62d8be107.png",
            "x": 162,
            "y": 311,
            "rotatedWidth": 147,
            "rotatedHeight": 147
          },
          {
            "name": "txkuang_vip8",
            "uuid": "47ae7542-1b65-4daa-84e0-8688fa54bf59",
            "textureUuid": "70dbc63d-cd2b-4b33-90d9-c276b535b1d2",
            "path": "D:\\cocos\\chinared\\temp\\trimImages\\spritesheet_js_1643348152144_image_4.png",
            "trim": {
              "x": 312,
              "y": 453,
              "width": 140,
              "height": 142,
              "rotatedWidth": 142,
              "rotatedHeight": 140
            },
            "rawWidth": 160,
            "rawHeight": 160,
            "width": 146,
            "height": 148,
            "originalPath": "D:/cocos/chinared/library/imports/70/70dbc63d-cd2b-4b33-90d9-c276b535b1d2.png",
            "x": 309,
            "y": 450,
            "rotated": true,
            "rotatedWidth": 148,
            "rotatedHeight": 146
          },
          {
            "name": "txkuang_vip7",
            "uuid": "e21f1c12-dca1-4a7f-bcf2-1ccdf980ffa5",
            "textureUuid": "1248025e-ac39-45b8-a121-6062e6b7f156",
            "path": "D:\\cocos\\chinared\\temp\\trimImages\\spritesheet_js_1643348152146_image_13.png",
            "trim": {
              "x": 3,
              "y": 316,
              "width": 142,
              "height": 138,
              "rotatedWidth": 142,
              "rotatedHeight": 138
            },
            "rawWidth": 160,
            "rawHeight": 160,
            "width": 148,
            "height": 144,
            "originalPath": "D:/cocos/chinared/library/imports/12/1248025e-ac39-45b8-a121-6062e6b7f156.png",
            "x": 0,
            "y": 313,
            "rotatedWidth": 148,
            "rotatedHeight": 144
          },
          {
            "name": "txkuang_vip5",
            "uuid": "634ed800-76d2-4f71-ab5b-08de17c1460c",
            "textureUuid": "015c1f4e-0930-42c8-9b82-cad67b422064",
            "path": "D:\\cocos\\chinared\\temp\\trimImages\\spritesheet_js_1643348152145_image_6.png",
            "trim": {
              "x": 3,
              "y": 460,
              "width": 140,
              "height": 137,
              "rotatedWidth": 140,
              "rotatedHeight": 137
            },
            "rawWidth": 160,
            "rawHeight": 160,
            "width": 146,
            "height": 143,
            "originalPath": "D:/cocos/chinared/library/imports/01/015c1f4e-0930-42c8-9b82-cad67b422064.png",
            "x": 0,
            "y": 457,
            "rotatedWidth": 146,
            "rotatedHeight": 143
          },
          {
            "name": "txkuang_vip3",
            "uuid": "8acd951f-9d4b-4208-b8a4-5fad2123ebb4",
            "textureUuid": "d1abf658-f9ec-4395-8d6b-7e541f72fae2",
            "path": "D:\\cocos\\chinared\\temp\\trimImages\\spritesheet_js_1643348152145_image_8.png",
            "trim": {
              "x": 149,
              "y": 461,
              "width": 138,
              "height": 137,
              "rotatedWidth": 138,
              "rotatedHeight": 137
            },
            "rawWidth": 160,
            "rawHeight": 160,
            "width": 144,
            "height": 143,
            "originalPath": "D:/cocos/chinared/library/imports/d1/d1abf658-f9ec-4395-8d6b-7e541f72fae2.png",
            "x": 146,
            "y": 458,
            "rotatedWidth": 144,
            "rotatedHeight": 143
          },
          {
            "name": "txkuang_vip2",
            "uuid": "eaee3e7d-22ab-4a48-ac7c-ed652d098303",
            "textureUuid": "52fcb99f-b299-47fc-b6c6-c0350c3dba61",
            "path": "D:\\cocos\\chinared\\temp\\trimImages\\spritesheet_js_1643348152146_image_14.png",
            "trim": {
              "x": 3,
              "y": 603,
              "width": 136,
              "height": 138,
              "rotatedWidth": 138,
              "rotatedHeight": 136
            },
            "rawWidth": 160,
            "rawHeight": 160,
            "width": 142,
            "height": 144,
            "originalPath": "D:/cocos/chinared/library/imports/52/52fcb99f-b299-47fc-b6c6-c0350c3dba61.png",
            "x": 0,
            "y": 600,
            "rotated": true,
            "rotatedWidth": 144,
            "rotatedHeight": 142
          },
          {
            "name": "txkuang_vip1",
            "uuid": "f98de3bb-5542-459b-a214-000f0647f462",
            "textureUuid": "964aca90-0c59-491b-b49f-7508e3c1cc07",
            "path": "D:\\cocos\\chinared\\temp\\trimImages\\spritesheet_js_1643348152146_image_15.png",
            "trim": {
              "x": 293,
              "y": 599,
              "width": 137,
              "height": 136,
              "rotatedWidth": 137,
              "rotatedHeight": 136
            },
            "rawWidth": 160,
            "rawHeight": 160,
            "width": 143,
            "height": 142,
            "originalPath": "D:/cocos/chinared/library/imports/96/964aca90-0c59-491b-b49f-7508e3c1cc07.png",
            "x": 290,
            "y": 596,
            "rotatedWidth": 143,
            "rotatedHeight": 142
          },
          {
            "name": "txkuang_vip4",
            "uuid": "362200f0-28eb-49c3-b855-83904801afe7",
            "textureUuid": "9e477f8f-7726-4b43-aa2b-4b04d5dd5f77",
            "path": "D:\\cocos\\chinared\\temp\\trimImages\\spritesheet_js_1643348152144_image_3.png",
            "trim": {
              "x": 147,
              "y": 604,
              "width": 132,
              "height": 138,
              "rotatedWidth": 138,
              "rotatedHeight": 132
            },
            "rawWidth": 160,
            "rawHeight": 160,
            "width": 138,
            "height": 144,
            "originalPath": "D:/cocos/chinared/library/imports/9e/9e477f8f-7726-4b43-aa2b-4b04d5dd5f77.png",
            "x": 144,
            "y": 601,
            "rotated": true,
            "rotatedWidth": 144,
            "rotatedHeight": 138
          },
          {
            "name": "txkuang_vip0",
            "uuid": "854dba15-39b9-4d28-8fca-57bcad564ff4",
            "textureUuid": "9d0f0a50-73da-4492-8158-d1bd08133665",
            "path": "D:\\cocos\\chinared\\temp\\trimImages\\spritesheet_js_1643348152145_image_7.png",
            "trim": {
              "x": 291,
              "y": 741,
              "width": 117,
              "height": 117,
              "rotatedWidth": 117,
              "rotatedHeight": 117
            },
            "rawWidth": 160,
            "rawHeight": 160,
            "width": 123,
            "height": 123,
            "originalPath": "D:/cocos/chinared/library/imports/9d/9d0f0a50-73da-4492-8158-d1bd08133665.png",
            "x": 288,
            "y": 738,
            "rotatedWidth": 123,
            "rotatedHeight": 123
          }
        ],
        "width": 491,
        "height": 861,
        "name": "game_head_kuang-1",
        "imagePath": "D:\\cocos\\chinared\\temp\\TexturePacker\\build\\native\\assets\\resources\\hall\\texture\\hall\\game_head_kuang\\game_head_kuang.pac\\game_head_kuang-1.png",
        "compressd": {
          "suffix": [
            ".png"
          ],
          "imagePathNoExt": "D:\\cocos\\chinared\\temp\\TexturePacker\\build\\native\\assets\\resources\\hall\\texture\\hall\\game_head_kuang\\game_head_kuang.pac\\compressed\\game_head_kuang-1"
        }
      }
    ],
    "unpackedTextures": []
  }
}