{"frameRate":24,"name":"21dian","version":"5.5","compatibleVersion":"5.5","armature":[{"type":"Armature","frameRate":24,"name":"Armature","aabb":{"x":-114,"y":-105.53,"width":235.95,"height":203},"bone":[{"name":"root"},{"length":51,"name":"21dian_wenzi","parent":"root","transform":{"y":82.1,"skX":-90,"skY":-90}},{"length":29,"name":"21dian_hongbao","parent":"root","transform":{"x":-101.1,"y":-13.55,"skX":87.4105,"skY":87.4105}},{"length":78,"name":"21dian_saizi","parent":"root","transform":{"x":-29.2,"y":52.95,"skX":-86.0411,"skY":-86.0411}},{"length":144,"name":"21dian_puke01","parent":"root","transform":{"x":29.85,"y":74.4201,"skX":-86.2386,"skY":-86.2386}},{"length":129,"name":"21dian_puke02","parent":"root","transform":{"x":14.25,"y":33.7201,"skX":-88.5193,"skY":-88.5193}},{"length":70,"name":"21dian_chouma02","parent":"root","transform":{"x":-1.05,"y":77.7501,"skX":-90,"skY":-90}},{"length":61,"name":"21dian_chouma01","parent":"root","transform":{"x":52.45,"y":41.75,"skX":-91.0331,"skY":-91.0331}},{"length":33,"name":"21dian_jinbi01","parent":"root","transform":{"x":105.5,"y":-48.15,"skX":132.4471,"skY":132.4471}}],"slot":[{"name":"21dian_puke02","parent":"21dian_puke02"},{"name":"21dian_puke01","parent":"21dian_puke01"},{"name":"21dian_chouma02","parent":"21dian_chouma02"},{"name":"21dian_saizi","parent":"21dian_saizi"},{"name":"21dian_chouma01","parent":"21dian_chouma01"},{"name":"21dian_hongbao","parent":"21dian_hongbao"},{"name":"21dian_jinbi01","parent":"21dian_jinbi01"},{"name":"21dian_wenzi","parent":"21dian_wenzi"}],"skin":[{"slot":[{"name":"21dian_saizi","display":[{"name":"21dian/21dian_saizi","transform":{"x":32.92,"y":-1.58,"skX":86.04,"skY":86.04}}]},{"name":"21dian_chouma02","display":[{"name":"21dian/21dian_chouma02","transform":{"x":35.55,"y":-0.45,"skX":90,"skY":90}}]},{"name":"21dian_puke02","display":[{"name":"21dian/21dian_puke02","transform":{"x":57.47,"y":-30.75,"skX":88.52,"skY":88.52}}]},{"name":"21dian_wenzi","display":[{"name":"21dian/21dian_wenzi","transform":{"x":24.1,"y":0.5,"skX":90,"skY":90}}]},{"name":"21dian_jinbi01","display":[{"name":"21dian/21dian_jinbi01","transform":{"x":18.49,"y":-6.68,"skX":-132.45,"skY":-132.45}}]},{"name":"21dian_hongbao","display":[{"name":"21dian/21dian_hongbao","transform":{"x":12.18,"y":-2.55,"skX":-87.41,"skY":-87.41}}]},{"name":"21dian_chouma01","display":[{"name":"21dian/21dian_chouma01","transform":{"x":21.25,"y":-0.07,"skX":91.03,"skY":91.03}}]},{"name":"21dian_puke01","display":[{"name":"21dian/21dian_puke01","transform":{"x":71.15,"y":-14.55,"skX":86.24,"skY":86.24}}]}]}],"animation":[{"duration":90,"playTimes":0,"name":"idle","bone":[{"name":"21dian_hongbao","translateFrame":[{"duration":45,"tweenEasing":0,"x":-7.71,"y":-12.45},{"duration":45,"tweenEasing":0,"x":4.95,"y":6.59},{"duration":0,"x":-7.71,"y":-12.45}],"rotateFrame":[{"duration":45,"tweenEasing":0,"rotate":-12.53},{"duration":45,"tweenEasing":0},{"duration":0,"rotate":-12.53}]},{"name":"21dian_saizi","translateFrame":[{"duration":45,"tweenEasing":0,"y":2.9},{"duration":45,"tweenEasing":0,"y":-23.08},{"duration":0,"y":2.9}],"rotateFrame":[{"duration":45,"tweenEasing":0},{"duration":45,"tweenEasing":0,"rotate":-6.3},{"duration":0}]},{"name":"21dian_puke01","translateFrame":[{"duration":45,"tweenEasing":0},{"duration":45,"tweenEasing":0,"x":4.67,"y":-16.68},{"duration":0}],"rotateFrame":[{"duration":45,"tweenEasing":0},{"duration":45,"tweenEasing":0,"rotate":4.17},{"duration":0}]},{"name":"21dian_puke02","translateFrame":[{"duration":45,"tweenEasing":0,"y":9.34},{"duration":45,"tweenEasing":0,"x":-2,"y":-8.01},{"duration":0,"y":9.34}],"rotateFrame":[{"duration":45,"tweenEasing":0},{"duration":45,"tweenEasing":0,"rotate":-2.53},{"duration":0}]},{"name":"21dian_chouma02","translateFrame":[{"duration":45,"tweenEasing":0,"y":-7.34},{"duration":45,"tweenEasing":0},{"duration":0,"y":-7.34}]},{"name":"21dian_chouma01","translateFrame":[{"duration":45,"tweenEasing":0,"y":4.12},{"duration":45,"tweenEasing":0,"x":6.67,"y":-15.23},{"duration":0,"y":4.12}],"rotateFrame":[{"duration":45,"tweenEasing":0},{"duration":45,"tweenEasing":0,"rotate":10.02},{"duration":0}]},{"name":"21dian_jinbi01","translateFrame":[{"duration":45,"tweenEasing":0},{"duration":45,"tweenEasing":0,"x":-8.01,"y":13.35},{"duration":0}],"rotateFrame":[{"duration":45,"tweenEasing":0},{"duration":45,"tweenEasing":0,"rotate":-17.3},{"duration":0}]}]}],"defaultActions":[{"gotoAndPlay":"idle"}]}]}