{"frameRate":24,"isGlobal":0,"name":"chongzhidonghua","version":"4.5","armature":[{"defaultActions":[{"gotoAndPlay":"idle"}],"skin":[{"name":"","slot":[{"display":[{"path":"chongzhizhu/chongzhi_zhutou","type":"image","name":"chongzhizhu/chongzhi_zhutou","transform":{"y":-6.6881,"skX":89.5996,"skY":89.5996,"x":34.0541}}],"name":"chongzhi_zhutou"},{"display":[{"path":"chongzhizhu/chongzhi_duzi","type":"image","name":"chongzhizhu/chongzhi_duzi","transform":{"y":-8.6629,"skX":87.0698,"skY":87.0698,"x":13.7251}}],"name":"chongzhi_duzi"},{"display":[{"path":"chongzhizhu/chongzhi_jinbi01","type":"image","name":"chongzhizhu/chongzhi_jinbi01","transform":{"y":-2.1205,"skX":87.9098,"skY":87.9098,"x":0.523}}],"name":"chongzhi_jinbi01"},{"display":[{"path":"chongzhizhu/chongzhi_jinbi02","type":"image","name":"chongzhizhu/chongzhi_jinbi02","transform":{"y":2.0635,"skX":87.6673,"skY":87.6673,"x":11.9939}}],"name":"chongzhi_jinbi02"},{"display":[{"uvs":[0.1415,0.28363,0.7545,0.07788,0.0015,0.92257,0.752,0.72832,1,0.28717,0.478,0,0.6765,0.98274,0.0445,0.53938,0.8495,0.52832,0.3325,0,0.86319,0.50638,0.15813,0.25893,0.03598,0.56415,0.76312,0.7055],"vertices":[-35.85,-24.45,25.45,-47.7,-49.85,47.75,25.2,25.8,50,-24.05,-2.2,-56.5,17.65,54.55,-45.55,4.45,34.95,3.2,-16.75,-56.5,36.32,0.72,-34.19,-27.24,-46.4,7.25,26.31,23.22],"edges":[1,4,5,1,3,6,6,2,9,5,7,0,4,10,10,8,0,11,11,9,2,12,12,7,8,13,13,3],"path":"chongzhizhu/chongzhi_duilian","weights":[2,4,0.2,7,0.8,1,4,1,1,8,1,2,8,0.8,7,0.2,1,4,1,1,4,1,1,8,1,2,8,0.2,7,0.8,2,4,0.2,7,0.8,1,4,1,2,4,0.8,7,0.2,2,4,0.8,7,0.2,2,8,0.8,7,0.2,2,7,0.8,8,0.2],"userEdges":[],"bonePose":[4,-0.35886061651163137,0.9333911601878881,-0.9333911601878881,-0.35886061651163137,46.15,-18.3,7,-0.32045034777056364,0.9472653137393583,-0.9472653137393583,-0.32045034777056364,36,7.600000000000001,8,-0.23103392744704074,0.9729456944600741,-0.9729456944600741,-0.23103392744704074,26.9,34.5],"type":"mesh","transform":{"y":-7.7963,"skX":-103.358,"skY":-103.358,"x":-15.2128},"slotPose":[1,0,0,1,37.999999999999986,21.499999999999982],"width":100,"height":113,"name":"chongzhizhu/chongzhi_duilian","triangles":[1,10,4,5,11,1,11,8,10,1,11,10,0,13,8,11,0,8,7,12,3,7,3,13,0,7,13,2,6,3,12,2,3,9,11,5]}],"name":"chongzhi_duilian"},{"display":[{"path":"chongzhizhu/chongzhi_yuanbao","type":"image","name":"chongzhizhu/chongzhi_yuanbao","transform":{"y":2.0584,"skX":82.5449,"skY":82.5449,"x":16.2545}}],"name":"chongzhi_yuanbao"}]}],"type":"Armature","name":"Armature","ik":[],"bone":[{"name":"root","transform":{}},{"length":27,"transform":{"y":6.6,"skX":-87.9098,"skY":-87.9098,"x":40.1},"parent":"root","name":"chongzhi_jinbi01"},{"length":40,"transform":{"y":46.15,"skX":-87.0698,"skY":-87.0698,"x":-2.55},"parent":"root","name":"chongzhi_duzi"},{"length":38,"transform":{"y":64.4,"skX":-87.6673,"skY":-87.6673,"x":-1.55},"parent":"root","name":"chongzhi_jinbi02"},{"length":28,"transform":{"y":45.3417,"skX":-161.8999,"skY":-161.8999,"x":66.8552},"parent":"chongzhi_duzi","name":"chongzhi_duilian"},{"length":71,"transform":{"y":-3.0205,"skX":-2.5298,"skY":-2.5298,"x":39.4472},"parent":"chongzhi_duzi","name":"chongzhi_zhutou"},{"length":31,"transform":{"y":-44.1325,"skX":4.525,"skY":4.525,"x":19.0689},"parent":"chongzhi_duzi","name":"chongzhi_yuanbao"},{"length":28,"transform":{"y":0.1794,"skX":-2.3401,"skY":-2.3401,"x":27.8173},"parent":"chongzhi_duilian","name":"chongzhi_duilian1"},{"length":30,"transform":{"skX":-5.3322,"skY":-5.3322,"x":28.3975},"parent":"chongzhi_duilian1","name":"chongzhi_duilian2"}],"aabb":{"width":222,"y":-78.00000000000001,"height":161,"x":-110},"slot":[{"name":"chongzhi_duzi","parent":"chongzhi_duzi","color":{}},{"z":1,"name":"chongzhi_zhutou","parent":"chongzhi_zhutou","color":{}},{"z":2,"name":"chongzhi_yuanbao","parent":"chongzhi_yuanbao","color":{}},{"z":3,"name":"chongzhi_duilian","parent":"chongzhi_duilian2","color":{}},{"z":4,"name":"chongzhi_jinbi02","parent":"chongzhi_jinbi02","color":{}},{"z":5,"name":"chongzhi_jinbi01","parent":"chongzhi_jinbi01","color":{}}],"animation":[{"frame":[],"duration":90,"ik":[],"bone":[{"frame":[{"duration":90,"transform":{}}],"name":"root"},{"frame":[{"tweenEasing":0,"duration":45,"transform":{"y":3.2922,"x":-0.1861}},{"tweenEasing":0,"duration":45,"transform":{"y":-2.5611,"skX":9.7744,"skY":9.7744,"x":-8.3729}},{"duration":0,"transform":{"y":3.2922,"x":-0.1861}}],"name":"chongzhi_jinbi01"},{"frame":[{"tweenEasing":0,"duration":5,"transform":{"skX":-3.676,"skY":-3.676}},{"tweenEasing":0,"duration":5,"transform":{"skX":12.5387,"skY":12.5387}},{"tweenEasing":0,"duration":5,"transform":{"skX":-3.676,"skY":-3.676}},{"tweenEasing":0,"duration":5,"transform":{"skX":4.3608,"skY":4.3608}},{"duration":70,"transform":{"skX":1.5859,"skY":1.5859}}],"name":"chongzhi_zhutou"},{"frame":[{"tweenEasing":0,"duration":8,"transform":{"skX":0.4052,"skY":0.4052}},{"tweenEasing":0,"duration":45,"transform":{"skX":1.7486,"skY":1.7486}},{"tweenEasing":0,"duration":37,"transform":{"skX":-5.8082,"skY":-5.8082}},{"duration":0,"transform":{"skX":0.4052,"skY":0.4052}}],"name":"chongzhi_duilian"},{"frame":[{"duration":90,"transform":{}}],"name":"chongzhi_duzi"},{"frame":[{"duration":20,"transform":{"y":0.0322,"x":-0.6297},"curve":[0.5,0,0.5,1]},{"duration":25,"transform":{"y":0.3546,"skX":12.0666,"skY":12.0666,"x":-6.9267},"curve":[0.5,0,0.5,1]},{"duration":30,"transform":{"y":0.0322,"x":-0.6297},"curve":[0.5,0,0.5,1]},{"duration":15,"transform":{"y":0.3546,"skX":12.0666,"skY":12.0666,"x":-6.9267},"curve":[0.5,0,0.5,1]},{"duration":0,"transform":{"y":0.0322,"x":-0.6297}}],"name":"chongzhi_yuanbao"},{"frame":[{"duration":90,"transform":{}}],"name":"chongzhi_jinbi02"},{"frame":[{"tweenEasing":0,"duration":16,"transform":{"skX":-3.2092,"skY":-3.2092}},{"tweenEasing":0,"duration":45,"transform":{}},{"tweenEasing":0,"duration":29,"transform":{"skX":-9.0259,"skY":-9.0259}},{"duration":0,"transform":{"skX":-3.2092,"skY":-3.2092}}],"name":"chongzhi_duilian1"},{"frame":[{"tweenEasing":0,"duration":24,"transform":{"skX":-4.1046,"skY":-4.1046}},{"tweenEasing":0,"duration":45,"transform":{}},{"tweenEasing":0,"duration":21,"transform":{"skX":-7.6961,"skY":-7.6961}},{"duration":0,"transform":{"skX":-4.1046,"skY":-4.1046}}],"name":"chongzhi_duilian2"}],"slot":[],"ffd":[],"name":"idle","playTimes":0}],"frameRate":24}]}