{
  "projectPath": "D:\\cocos\\chinared",
  "actualPlatform": "web-mobile",
  "mtimes": {
    "70736ddd-3a60-4d21-b924-7108226dc1ae": {
      "assetMtime": 1636537563503,
      "metaMtime": 1643191094011
    },
    "295fb975-41f1-4ab9-90f6-9f5876569d89": {
      "assetMtime": 1636537563511,
      "metaMtime": 1643191094116
    },
    "29d8becf-c99e-47f2-8680-92bd452d094f": {
      "assetMtime": 1636537563511,
      "metaMtime": 1643191094116
    },
    "50e2cb26-29cb-4919-9e3d-3b642684619d": {
      "assetMtime": 1636537563507,
      "metaMtime": 1643191094064
    },
    "044555e5-8a71-47f9-8d62-1ba8f8d374c4": {
      "assetMtime": 1636537563507,
      "metaMtime": 1643191094064
    },
    "70684651-8188-4a7b-b9e5-2a8711e2e2d6": {
      "assetMtime": 1636537563510,
      "metaMtime": 1643191094102
    },
    "36e30225-a160-499a-ad1d-01ffa95dfefb": {
      "assetMtime": 1636537563510,
      "metaMtime": 1643191094102
    },
    "80ecb02b-a364-4a0f-a2b8-cb4da4078306": {
      "assetMtime": 1636537563508,
      "metaMtime": 1643191094067
    },
    "b95faaec-bcb3-4b0f-a78a-4157458300d7": {
      "assetMtime": 1636537563508,
      "metaMtime": 1643191094067
    },
    "8a32b53b-03a3-47c9-b7ae-fd36a7d05ffe": {
      "assetMtime": 1636537563506,
      "metaMtime": 1643191094047
    },
    "fd157020-f96f-43a2-ba8c-3ceca807b5af": {
      "assetMtime": 1636537563506,
      "metaMtime": 1643191094047
    },
    "94768522-c85e-4b78-a609-319cd325a153": {
      "assetMtime": 1636537563508,
      "metaMtime": 1643191094079
    },
    "76e1cc6d-c205-4862-8d8c-19668734e130": {
      "assetMtime": 1636537563508,
      "metaMtime": 1643191094079
    },
    "97164394-e89c-46b2-841c-0b0d72802bb0": {
      "assetMtime": 1636537563510,
      "metaMtime": 1643191094092
    },
    "2ab2ff6b-bf6c-4583-a770-7f80cef73996": {
      "assetMtime": 1636537563510,
      "metaMtime": 1643191094092
    },
    "9eaed31b-de57-4f55-a662-4bb38c48558f": {
      "assetMtime": 1636537563505,
      "metaMtime": 1643191094036
    },
    "e8833e21-9ed7-4c9a-9efc-f094239846ef": {
      "assetMtime": 1636537563505,
      "metaMtime": 1643191094036
    },
    "a354df0c-8a94-4d28-a349-a2a2f33cccfe": {
      "assetMtime": 1636537563504,
      "metaMtime": 1643191094027
    },
    "a6d6acf6-7780-4c9f-a6bb-47d659b39f77": {
      "assetMtime": 1636537563504,
      "metaMtime": 1643191094027
    },
    "ab7b5c6c-9c7f-4ecf-a400-52607fad24d4": {
      "assetMtime": 1636537563506,
      "metaMtime": 1643191094050
    },
    "579e3a03-5868-463d-910f-05611a0e9b26": {
      "assetMtime": 1636537563506,
      "metaMtime": 1643191094050
    },
    "b483b795-98bd-4906-9992-4335cad88e0d": {
      "assetMtime": 1636537563505,
      "metaMtime": 1643191094038
    },
    "54cbc9a1-a15c-45ca-898b-f8179a2679f7": {
      "assetMtime": 1636537563505,
      "metaMtime": 1643191094038
    },
    "e80ab1d4-eba2-48b7-b0ef-05471b31358d": {
      "assetMtime": 1636537563504,
      "metaMtime": 1643191094024
    },
    "70af779b-3031-4c85-9260-f0c3ec7c43b7": {
      "assetMtime": 1636537563504,
      "metaMtime": 1643191094024
    },
    "eb07274f-1c18-46ab-83ec-1ffe06cf668c": {
      "assetMtime": 1636537563509,
      "metaMtime": 1643191094080
    },
    "c76a9174-83e5-48ec-b8ad-93bbc56fbc4e": {
      "assetMtime": 1636537563509,
      "metaMtime": 1643191094080
    },
    "f65d56c4-3741-4369-aa3b-028a7d4766a1": {
      "assetMtime": 1636537563509,
      "metaMtime": 1643191094089
    },
    "6369058c-92bd-4f2e-bf7a-674463181a5d": {
      "assetMtime": 1636537563509,
      "metaMtime": 1643191094089
    },
    "fcb787c9-74e6-47bb-830e-a14241c596cf": {
      "assetMtime": 1636537563511,
      "metaMtime": 1643191094103
    },
    "9c3f8aa6-1de8-4775-8e27-d9361ceecfe0": {
      "assetMtime": 1636537563511,
      "metaMtime": 1643191094103
    }
  },
  "result": {
    "name": "atlas_frame",
    "width": 1024,
    "height": 1024,
    "ver": "1.2.1",
    "uuid": "70736ddd-3a60-4d21-b924-7108226dc1ae",
    "maxWidth": 1024,
    "maxHeight": 1024,
    "padding": 2,
    "allowRotation": true,
    "forceSquared": false,
    "powerOfTwo": true,
    "algorithm": "MaxRects",
    "format": "png",
    "quality": 80,
    "contourBleed": true,
    "paddingBleed": true,
    "filterUnused": true,
    "packable": false,
    "premultiplyAlpha": false,
    "filterMode": "bilinear",
    "platformSettings": {},
    "subMetas": {},
    "bleed": 1,
    "atlases": [
      {
        "files": [
          {
            "name": "ddz_zhuozi_03",
            "uuid": "9eaed31b-de57-4f55-a662-4bb38c48558f",
            "textureUuid": "e8833e21-9ed7-4c9a-9efc-f094239846ef",
            "path": "D:\\cocos\\chinared\\temp\\trimImages\\spritesheet_js_1643348182974_image_7.png",
            "trim": {
              "x": 3,
              "y": 3,
              "width": 252,
              "height": 103,
              "rotatedWidth": 252,
              "rotatedHeight": 103
            },
            "rawWidth": 252,
            "rawHeight": 103,
            "width": 258,
            "height": 109,
            "originalPath": "D:/cocos/chinared/library/imports/e8/e8833e21-9ed7-4c9a-9efc-f094239846ef.png",
            "x": 0,
            "y": 0,
            "rotatedWidth": 258,
            "rotatedHeight": 109
          },
          {
            "name": "ddz_zhuozi_01",
            "uuid": "e80ab1d4-eba2-48b7-b0ef-05471b31358d",
            "textureUuid": "70af779b-3031-4c85-9260-f0c3ec7c43b7",
            "path": "D:\\cocos\\chinared\\temp\\trimImages\\spritesheet_js_1643348182975_image_11.png",
            "trim": {
              "x": 3,
              "y": 112,
              "width": 251,
              "height": 101,
              "rotatedWidth": 251,
              "rotatedHeight": 101
            },
            "rawWidth": 251,
            "rawHeight": 101,
            "width": 257,
            "height": 107,
            "originalPath": "D:/cocos/chinared/library/imports/70/70af779b-3031-4c85-9260-f0c3ec7c43b7.png",
            "x": 0,
            "y": 109,
            "rotatedWidth": 257,
            "rotatedHeight": 107
          },
          {
            "name": "num_fu_0",
            "uuid": "50e2cb26-29cb-4919-9e3d-3b642684619d",
            "textureUuid": "044555e5-8a71-47f9-8d62-1ba8f8d374c4",
            "path": "D:\\cocos\\chinared\\temp\\trimImages\\spritesheet_js_1643348182973_image_1.png",
            "trim": {
              "x": 3,
              "y": 219,
              "width": 251,
              "height": 99,
              "rotatedWidth": 251,
              "rotatedHeight": 99
            },
            "rawWidth": 256,
            "rawHeight": 128,
            "width": 257,
            "height": 105,
            "originalPath": "D:/cocos/chinared/library/imports/04/044555e5-8a71-47f9-8d62-1ba8f8d374c4.png",
            "x": 0,
            "y": 216,
            "rotatedWidth": 257,
            "rotatedHeight": 105
          },
          {
            "name": "num_jia_0",
            "uuid": "80ecb02b-a364-4a0f-a2b8-cb4da4078306",
            "textureUuid": "b95faaec-bcb3-4b0f-a78a-4157458300d7",
            "path": "D:\\cocos\\chinared\\temp\\trimImages\\spritesheet_js_1643348182973_image_3.png",
            "trim": {
              "x": 3,
              "y": 324,
              "width": 251,
              "height": 99,
              "rotatedWidth": 251,
              "rotatedHeight": 99
            },
            "rawWidth": 256,
            "rawHeight": 128,
            "width": 257,
            "height": 105,
            "originalPath": "D:/cocos/chinared/library/imports/b9/b95faaec-bcb3-4b0f-a78a-4157458300d7.png",
            "x": 0,
            "y": 321,
            "rotatedWidth": 257,
            "rotatedHeight": 105
          },
          {
            "name": "ddz_zhuozi_06",
            "uuid": "8a32b53b-03a3-47c9-b7ae-fd36a7d05ffe",
            "textureUuid": "fd157020-f96f-43a2-ba8c-3ceca807b5af",
            "path": "D:\\cocos\\chinared\\temp\\trimImages\\spritesheet_js_1643348182974_image_4.png",
            "trim": {
              "x": 3,
              "y": 429,
              "width": 209,
              "height": 34,
              "rotatedWidth": 209,
              "rotatedHeight": 34
            },
            "rawWidth": 209,
            "rawHeight": 34,
            "width": 215,
            "height": 40,
            "originalPath": "D:/cocos/chinared/library/imports/fd/fd157020-f96f-43a2-ba8c-3ceca807b5af.png",
            "x": 0,
            "y": 426,
            "rotatedWidth": 215,
            "rotatedHeight": 40
          },
          {
            "name": "fonts_bujiabei",
            "uuid": "70684651-8188-4a7b-b9e5-2a8711e2e2d6",
            "textureUuid": "36e30225-a160-499a-ad1d-01ffa95dfefb",
            "path": "D:\\cocos\\chinared\\temp\\trimImages\\spritesheet_js_1643348182973_image_2.png",
            "trim": {
              "x": 3,
              "y": 469,
              "width": 161,
              "height": 56,
              "rotatedWidth": 161,
              "rotatedHeight": 56
            },
            "rawWidth": 161,
            "rawHeight": 56,
            "width": 167,
            "height": 62,
            "originalPath": "D:/cocos/chinared/library/imports/36/36e30225-a160-499a-ad1d-01ffa95dfefb.png",
            "x": 0,
            "y": 466,
            "rotatedWidth": 167,
            "rotatedHeight": 62
          },
          {
            "name": "fonts_jiabei",
            "uuid": "295fb975-41f1-4ab9-90f6-9f5876569d89",
            "textureUuid": "29d8becf-c99e-47f2-8680-92bd452d094f",
            "path": "D:\\cocos\\chinared\\temp\\trimImages\\spritesheet_js_1643348182973_image_0.png",
            "trim": {
              "x": 170,
              "y": 469,
              "width": 109,
              "height": 56,
              "rotatedWidth": 56,
              "rotatedHeight": 109
            },
            "rawWidth": 109,
            "rawHeight": 56,
            "width": 115,
            "height": 62,
            "originalPath": "D:/cocos/chinared/library/imports/29/29d8becf-c99e-47f2-8680-92bd452d094f.png",
            "x": 167,
            "y": 466,
            "rotated": true,
            "rotatedWidth": 62,
            "rotatedHeight": 115
          },
          {
            "name": "ddz_zhuozi_05",
            "uuid": "ab7b5c6c-9c7f-4ecf-a400-52607fad24d4",
            "textureUuid": "579e3a03-5868-463d-910f-05611a0e9b26",
            "path": "D:\\cocos\\chinared\\temp\\trimImages\\spritesheet_js_1643348182974_image_9.png",
            "trim": {
              "x": 3,
              "y": 531,
              "width": 152,
              "height": 46,
              "rotatedWidth": 152,
              "rotatedHeight": 46
            },
            "rawWidth": 152,
            "rawHeight": 46,
            "width": 158,
            "height": 52,
            "originalPath": "D:/cocos/chinared/library/imports/57/579e3a03-5868-463d-910f-05611a0e9b26.png",
            "x": 0,
            "y": 528,
            "rotatedWidth": 158,
            "rotatedHeight": 52
          },
          {
            "name": "fonts_buchu",
            "uuid": "97164394-e89c-46b2-841c-0b0d72802bb0",
            "textureUuid": "2ab2ff6b-bf6c-4583-a770-7f80cef73996",
            "path": "D:\\cocos\\chinared\\temp\\trimImages\\spritesheet_js_1643348182974_image_6.png",
            "trim": {
              "x": 3,
              "y": 583,
              "width": 105,
              "height": 56,
              "rotatedWidth": 105,
              "rotatedHeight": 56
            },
            "rawWidth": 105,
            "rawHeight": 56,
            "width": 111,
            "height": 62,
            "originalPath": "D:/cocos/chinared/library/imports/2a/2ab2ff6b-bf6c-4583-a770-7f80cef73996.png",
            "x": 0,
            "y": 580,
            "rotatedWidth": 111,
            "rotatedHeight": 62
          },
          {
            "name": "fonts_bujiao",
            "uuid": "fcb787c9-74e6-47bb-830e-a14241c596cf",
            "textureUuid": "9c3f8aa6-1de8-4775-8e27-d9361ceecfe0",
            "path": "D:\\cocos\\chinared\\temp\\trimImages\\spritesheet_js_1643348182975_image_14.png",
            "trim": {
              "x": 114,
              "y": 584,
              "width": 105,
              "height": 55,
              "rotatedWidth": 105,
              "rotatedHeight": 55
            },
            "rawWidth": 105,
            "rawHeight": 55,
            "width": 111,
            "height": 61,
            "originalPath": "D:/cocos/chinared/library/imports/9c/9c3f8aa6-1de8-4775-8e27-d9361ceecfe0.png",
            "x": 111,
            "y": 581,
            "rotatedWidth": 111,
            "rotatedHeight": 61
          },
          {
            "name": "ddz_zhuozi_02",
            "uuid": "a354df0c-8a94-4d28-a349-a2a2f33cccfe",
            "textureUuid": "a6d6acf6-7780-4c9f-a6bb-47d659b39f77",
            "path": "D:\\cocos\\chinared\\temp\\trimImages\\spritesheet_js_1643348182974_image_8.png",
            "trim": {
              "x": 3,
              "y": 645,
              "width": 259,
              "height": 89,
              "rotatedWidth": 89,
              "rotatedHeight": 259
            },
            "rawWidth": 259,
            "rawHeight": 89,
            "width": 265,
            "height": 95,
            "originalPath": "D:/cocos/chinared/library/imports/a6/a6d6acf6-7780-4c9f-a6bb-47d659b39f77.png",
            "x": 0,
            "y": 642,
            "rotated": true,
            "rotatedWidth": 95,
            "rotatedHeight": 265
          },
          {
            "name": "fonts_3fen",
            "uuid": "f65d56c4-3741-4369-aa3b-028a7d4766a1",
            "textureUuid": "6369058c-92bd-4f2e-bf7a-674463181a5d",
            "path": "D:\\cocos\\chinared\\temp\\trimImages\\spritesheet_js_1643348182975_image_13.png",
            "trim": {
              "x": 3,
              "y": 910,
              "width": 88,
              "height": 55,
              "rotatedWidth": 55,
              "rotatedHeight": 88
            },
            "rawWidth": 88,
            "rawHeight": 55,
            "width": 94,
            "height": 61,
            "originalPath": "D:/cocos/chinared/library/imports/63/6369058c-92bd-4f2e-bf7a-674463181a5d.png",
            "x": 0,
            "y": 907,
            "rotated": true,
            "rotatedWidth": 61,
            "rotatedHeight": 94
          },
          {
            "name": "fonts_1fen",
            "uuid": "94768522-c85e-4b78-a609-319cd325a153",
            "textureUuid": "76e1cc6d-c205-4862-8d8c-19668734e130",
            "path": "D:\\cocos\\chinared\\temp\\trimImages\\spritesheet_js_1643348182974_image_5.png",
            "trim": {
              "x": 64,
              "y": 910,
              "width": 87,
              "height": 55,
              "rotatedWidth": 55,
              "rotatedHeight": 87
            },
            "rawWidth": 87,
            "rawHeight": 55,
            "width": 93,
            "height": 61,
            "originalPath": "D:/cocos/chinared/library/imports/76/76e1cc6d-c205-4862-8d8c-19668734e130.png",
            "x": 61,
            "y": 907,
            "rotated": true,
            "rotatedWidth": 61,
            "rotatedHeight": 93
          },
          {
            "name": "ddz_zhuozi_04",
            "uuid": "b483b795-98bd-4906-9992-4335cad88e0d",
            "textureUuid": "54cbc9a1-a15c-45ca-898b-f8179a2679f7",
            "path": "D:\\cocos\\chinared\\temp\\trimImages\\spritesheet_js_1643348182974_image_10.png",
            "trim": {
              "x": 98,
              "y": 645,
              "width": 254,
              "height": 102,
              "rotatedWidth": 102,
              "rotatedHeight": 254
            },
            "rawWidth": 254,
            "rawHeight": 102,
            "width": 260,
            "height": 108,
            "originalPath": "D:/cocos/chinared/library/imports/54/54cbc9a1-a15c-45ca-898b-f8179a2679f7.png",
            "x": 95,
            "y": 642,
            "rotated": true,
            "rotatedWidth": 108,
            "rotatedHeight": 260
          },
          {
            "name": "fonts_2fen",
            "uuid": "eb07274f-1c18-46ab-83ec-1ffe06cf668c",
            "textureUuid": "c76a9174-83e5-48ec-b8ad-93bbc56fbc4e",
            "path": "D:\\cocos\\chinared\\temp\\trimImages\\spritesheet_js_1643348182975_image_12.png",
            "trim": {
              "x": 125,
              "y": 905,
              "width": 87,
              "height": 55,
              "rotatedWidth": 55,
              "rotatedHeight": 87
            },
            "rawWidth": 87,
            "rawHeight": 55,
            "width": 93,
            "height": 61,
            "originalPath": "D:/cocos/chinared/library/imports/c7/c76a9174-83e5-48ec-b8ad-93bbc56fbc4e.png",
            "x": 122,
            "y": 902,
            "rotated": true,
            "rotatedWidth": 61,
            "rotatedHeight": 93
          }
        ],
        "width": 512,
        "height": 1024,
        "name": "atlas_frame-1",
        "imagePath": "D:\\cocos\\chinared\\temp\\TexturePacker\\build\\native\\assets\\ddz\\ddz\\texture\\atlas\\frame\\atlas_frame.pac\\atlas_frame-1.png",
        "compressd": {
          "suffix": [
            ".png"
          ],
          "imagePathNoExt": "D:\\cocos\\chinared\\temp\\TexturePacker\\build\\native\\assets\\ddz\\ddz\\texture\\atlas\\frame\\atlas_frame.pac\\compressed\\atlas_frame-1"
        }
      }
    ],
    "unpackedTextures": []
  }
}