{
  "__type__": "cc.TextAsset",
  "_name": "winDDZ.atlas",
  "_objFlags": 0,
  "_native": "",
  "text": "\r\nwinDDZ.png\r\nsize: 1024,512\r\nformat: RGBA8888\r\nfilter: Linear,Linear\r\nrepeat: none\r\n0101piaodai\r\n  rotate: true\r\n  xy: 751, 288\r\n  size: 41, 73\r\n  orig: 41, 73\r\n  offset: 0, 0\r\n  index: -1\r\n0103piaodai\r\n  rotate: false\r\n  xy: 50, 3\r\n  size: 45, 25\r\n  orig: 45, 25\r\n  offset: 0, 0\r\n  index: -1\r\n0104piaodai\r\n  rotate: false\r\n  xy: 751, 250\r\n  size: 48, 36\r\n  orig: 48, 36\r\n  offset: 0, 0\r\n  index: -1\r\n0105piaodai\r\n  rotate: false\r\n  xy: 826, 288\r\n  size: 60, 41\r\n  orig: 60, 41\r\n  offset: 0, 0\r\n  index: -1\r\n0108shengli\r\n  rotate: false\r\n  xy: 285, 34\r\n  size: 144, 55\r\n  orig: 144, 55\r\n  offset: 0, 0\r\n  index: -1\r\n0109huangguan\r\n  rotate: false\r\n  xy: 431, 34\r\n  size: 72, 55\r\n  orig: 72, 55\r\n  offset: 0, 0\r\n  index: -1\r\n0110shengliditu\r\n  rotate: false\r\n  xy: 285, 91\r\n  size: 365, 71\r\n  orig: 365, 71\r\n  offset: 0, 0\r\n  index: -1\r\n0111piaodai\r\n  rotate: true\r\n  xy: 2, 2\r\n  size: 26, 46\r\n  orig: 27, 50\r\n  offset: 0, 2\r\n  index: -1\r\n0112piaodai\r\n  rotate: false\r\n  xy: 888, 285\r\n  size: 55, 44\r\n  orig: 55, 44\r\n  offset: 0, 0\r\n  index: -1\r\n0115piaodai\r\n  rotate: true\r\n  xy: 652, 125\r\n  size: 37, 23\r\n  orig: 38, 23\r\n  offset: 0, 0\r\n  index: -1\r\n0116piaodai\r\n  rotate: false\r\n  xy: 635, 316\r\n  size: 35, 13\r\n  orig: 35, 13\r\n  offset: 0, 0\r\n  index: -1\r\n0118piaodai\r\n  rotate: false\r\n  xy: 995, 489\r\n  size: 27, 21\r\n  orig: 27, 21\r\n  offset: 0, 0\r\n  index: -1\r\n0119ditu\r\n  rotate: false\r\n  xy: 2, 313\r\n  size: 631, 197\r\n  orig: 631, 197\r\n  offset: 0, 0\r\n  index: -1\r\n0120guang\r\n  rotate: false\r\n  xy: 2, 30\r\n  size: 281, 281\r\n  orig: 281, 281\r\n  offset: 0, 0\r\n  index: -1\r\n3333330001\r\n  rotate: false\r\n  xy: 801, 251\r\n  size: 42, 35\r\n  orig: 42, 35\r\n  offset: 0, 0\r\n  index: -1\r\n3333330002\r\n  rotate: false\r\n  xy: 680, 161\r\n  size: 64, 50\r\n  orig: 64, 50\r\n  offset: 0, 0\r\n  index: -1\r\n3333330003\r\n  rotate: false\r\n  xy: 680, 272\r\n  size: 69, 57\r\n  orig: 69, 57\r\n  offset: 0, 0\r\n  index: -1\r\n3333330004\r\n  rotate: false\r\n  xy: 505, 31\r\n  size: 71, 58\r\n  orig: 71, 58\r\n  offset: 0, 0\r\n  index: -1\r\n3333330005\r\n  rotate: false\r\n  xy: 505, 31\r\n  size: 71, 58\r\n  orig: 71, 58\r\n  offset: 0, 0\r\n  index: -1\r\n3333330006\r\n  rotate: false\r\n  xy: 578, 32\r\n  size: 70, 57\r\n  orig: 70, 57\r\n  offset: 0, 0\r\n  index: -1\r\n3333330007\r\n  rotate: false\r\n  xy: 578, 32\r\n  size: 70, 57\r\n  orig: 70, 57\r\n  offset: 0, 0\r\n  index: -1\r\n3333330008\r\n  rotate: false\r\n  xy: 680, 213\r\n  size: 64, 57\r\n  orig: 64, 57\r\n  offset: 0, 0\r\n  index: -1\r\n3333330009\r\n  rotate: false\r\n  xy: 680, 213\r\n  size: 64, 57\r\n  orig: 64, 57\r\n  offset: 0, 0\r\n  index: -1\r\n3333330010\r\n  rotate: true\r\n  xy: 945, 288\r\n  size: 41, 45\r\n  orig: 41, 45\r\n  offset: 0, 0\r\n  index: -1\r\ng_01\r\n  rotate: false\r\n  xy: 635, 331\r\n  size: 358, 179\r\n  orig: 358, 179\r\n  offset: 0, 0\r\n  index: -1\r\nguangdi\r\n  rotate: false\r\n  xy: 285, 164\r\n  size: 393, 147\r\n  orig: 401, 147\r\n  offset: 4, 0\r\n  index: -1\r\nxingxing\r\n  rotate: false\r\n  xy: 845, 252\r\n  size: 33, 34\r\n  orig: 33, 34\r\n  offset: 0, 0\r\n  index: -1\r\n"
}